proxify3/__init__.py
proxify3/proxify.py
proxify3-0.0.3.dist-info/LICENSE
proxify3-0.0.3.dist-info/METADATA
proxify3-0.0.3.dist-info/WHEEL
proxify3-0.0.3.dist-info/top_level.txt
proxify3-0.0.3.dist-info/RECORD
