Metadata-Version: 2.1
Name: proxify3
Version: 0.0.3
Summary: A version of the original proxify by Somdev Sangwan that is compatable for recent versions of python.  I was recommended his tool, but upon trying to get it from pip/pip3 I encountered version errors. So I decided to download his source code, see the compatability problem, fix it, and reupload it to PyPi as proxify3
Home-page: https://github.com/ShivamPatelShivamPatel/Proxify3
Author: Shivam Patel
Author-email: shivamworkemail1@gmail.com
License: UNKNOWN
Project-URL: Bug Tracker, https://github.com/ShivamPatelShivamPatel/Proxify3/issues
Platform: UNKNOWN
Classifier: Programming Language :: Python :: 3
Classifier: License :: OSI Approved :: GNU General Public License v3 (GPLv3)
Classifier: Operating System :: OS Independent
Requires-Python: >=3
License-File: LICENSE
